multioptpy/__init__.py
multioptpy/entrypoints.py
multioptpy/fileio.py
multioptpy/ieip.py
multioptpy/interface.py
multioptpy/irc.py
multioptpy/moleculardynamics.py
multioptpy/neb.py
multioptpy/optimization.py
multioptpy/optimizer.py
multioptpy/Calculator/__init__.py
multioptpy/Calculator/ase_calculation_tools.py
multioptpy/Calculator/dxtb_calculation_tools.py
multioptpy/Calculator/emt_calculation_tools.py
multioptpy/Calculator/gpaw_calculation_tools.py
multioptpy/Calculator/lj_calculation_tools.py
multioptpy/Calculator/psi4_calculation_tools.py
multioptpy/Calculator/pwscf_calculation_tools.py
multioptpy/Calculator/pyscf_calculation_tools.py
multioptpy/Calculator/sqm1_calculation_tools.py
multioptpy/Calculator/sqm2_calculation_tools.py
multioptpy/Calculator/tblite_calculation_tools.py
multioptpy/Calculator/tersoff_calculation_tools.py
multioptpy/Calculator/ase_tools/__init__.py
multioptpy/Calculator/ase_tools/fairchem.py
multioptpy/Calculator/ase_tools/gamess.py
multioptpy/Calculator/ase_tools/gaussian.py
multioptpy/Calculator/ase_tools/gxtb_dev.py
multioptpy/Calculator/ase_tools/mace.py
multioptpy/Calculator/ase_tools/mopac.py
multioptpy/Calculator/ase_tools/nwchem.py
multioptpy/Calculator/ase_tools/orca.py
multioptpy/Calculator/ase_tools/pygfn0.py
multioptpy/Constraint/__init__.py
multioptpy/Constraint/constraint_condition.py
multioptpy/Coordinate/__init__.py
multioptpy/Coordinate/polar_coordinate.py
multioptpy/Coordinate/redundant_coordinate.py
multioptpy/IRC/__init__.py
multioptpy/IRC/converge_criteria.py
multioptpy/IRC/dvv.py
multioptpy/IRC/euler.py
multioptpy/IRC/hpc.py
multioptpy/IRC/lqa.py
multioptpy/IRC/modekill.py
multioptpy/IRC/rk4.py
multioptpy/Interpolation/__init__.py
multioptpy/Interpolation/adaptive_interpolation.py
multioptpy/Interpolation/binomial_interpolation.py
multioptpy/Interpolation/geodesic_interpolation.py
multioptpy/Interpolation/interpolation.py
multioptpy/Interpolation/linear_interpolation.py
multioptpy-1.20.7.dist-info/licenses/LICENSE
multioptpy-1.20.7.dist-info/METADATA
multioptpy-1.20.7.dist-info/WHEEL
multioptpy-1.20.7.dist-info/entry_points.txt
multioptpy-1.20.7.dist-info/top_level.txt
multioptpy-1.20.7.dist-info/RECORD
