Metadata-Version: 2.4
Name: MultiOptPy
Version: 1.20.7
Summary: Multifunctional geometry optimization tools for quantum chemical calculations.
Author-email: ss0832 <highlighty876@gmail.com>
License-Expression: GPL-3.0-or-later
Requires-Python: >=3.12
License-File: LICENSE
Requires-Dist: numpy>=2.2.0
Requires-Dist: scipy>=1.13.0
Requires-Dist: matplotlib>=3.10.0
Requires-Dist: torch~=2.6.0
Requires-Dist: pyscf>=2.9.0
Requires-Dist: tblite==0.4.0
Requires-Dist: ase~=3.26.0
Requires-Dist: fairchem-core~=2.7.0
Requires-Dist: sympy>=1.13.0
Dynamic: license-file
